LICENSE
README.md
nautobot_plugin_chatops_aci/__init__.py
nautobot_plugin_chatops_aci/aci.py
nautobot_plugin_chatops_aci/static/nautobot_plugin_chatops_aci/.gitignore
nautobot_plugin_chatops_aci/static/nautobot_plugin_chatops_aci/aci-transparent.png
nautobot_plugin_chatops_aci/static/nautobot_plugin_chatops_aci/cisco-aci-transparent-1.png
nautobot_plugin_chatops_aci/static/nautobot_plugin_chatops_aci/cisco-logo-transparent.png
nautobot_plugin_chatops_aci/static/nautobot_plugin_chatops_aci/csco-logo.png
nautobot_plugin_chatops_aci/tests/__init__.py
nautobot_plugin_chatops_aci/tests/test_aci.py
nautobot_plugin_chatops_aci/tests/test_basic.py
nautobot_plugin_chatops_aci/utils.py
nautobot_plugin_chatops_aci/worker.py
nautobot_plugin_chatops_aci-1.0.0.dist-info/entry_points.txt
nautobot_plugin_chatops_aci-1.0.0.dist-info/LICENSE
nautobot_plugin_chatops_aci-1.0.0.dist-info/WHEEL
nautobot_plugin_chatops_aci-1.0.0.dist-info/METADATA
nautobot_plugin_chatops_aci-1.0.0.dist-info/RECORD
