Metadata-Version: 2.1
Name: nautobot-plugin-chatops-aci
Version: 1.0.0
Summary: Nautobot Plugin Chatops Cisco ACI
Home-page: https://github.com/nautobot/nautobot-plugin-chatops-aci
License: Apache-2.0
Keywords: nautobot,nautobot-plugin,nautobot-chatops-plugin
Author: Network to Code, LLC
Author-email: info@networktocode.com
Requires-Python: >=3.6.2,<4.0.0
Classifier: License :: OSI Approved :: Apache Software License
Classifier: Programming Language :: Python :: 3
Classifier: Programming Language :: Python :: 3.10
Classifier: Programming Language :: Python :: 3.7
Classifier: Programming Language :: Python :: 3.8
Classifier: Programming Language :: Python :: 3.9
Requires-Dist: importlib-metadata (>=3.5)
Requires-Dist: nautobot
Requires-Dist: nautobot-chatops (>=1.5,<2.0)
Requires-Dist: prettytable (>=2.1.0,<3.0.0)
Project-URL: Repository, https://github.com/nautobot/nautobot-plugin-chatops-aci
